cloe_dbx_connector/__init__.py
cloe_dbx_connector/config.py
cloe_dbx_connector/connector.py
cloe_dbx_connector/main.py
cloe_dbx_connector/py.typed
cloe_dbx_connector-1.0.0.dist-info/METADATA
cloe_dbx_connector-1.0.0.dist-info/WHEEL
cloe_dbx_connector-1.0.0.dist-info/RECORD
