Metadata-Version: 2.4
Name: cloe-dbx-connector
Version: 1.0.0
Summary: This package provides a simple wrapper around the Databricks SDK's `WorkspaceClient` that supports Azure Databricks authentication using Personal Access Token (PAT) or Azure Service Principal credentials.
Author-email: initions <ICSMC_EXT_PYPIORG@accenture.com>
License: MIT
Classifier: Development Status :: 5 - Production/Stable
Classifier: Environment :: Console
Classifier: Intended Audience :: Developers
Classifier: License :: OSI Approved :: MIT License
Classifier: Operating System :: OS Independent
Classifier: Programming Language :: Python :: 3
Classifier: Topic :: Database
Requires-Python: <3.14,>=3.13
Requires-Dist: cloe-logging>=0.3.7
Requires-Dist: databricks-sdk~=0.41
Requires-Dist: pydantic-settings>=2.7.1
Requires-Dist: pydantic~=2.10
Requires-Dist: pytest~=8.4.0
